.long-description.html
README.rst
setup.py
src/collective/__init__.py
src/collective.behavior.sku.egg-info/PKG-INFO
src/collective.behavior.sku.egg-info/SOURCES.txt
src/collective.behavior.sku.egg-info/dependency_links.txt
src/collective.behavior.sku.egg-info/entry_points.txt
src/collective.behavior.sku.egg-info/namespace_packages.txt
src/collective.behavior.sku.egg-info/not-zip-safe
src/collective.behavior.sku.egg-info/requires.txt
src/collective.behavior.sku.egg-info/top_level.txt
src/collective/behavior/__init__.py
src/collective/behavior/sku/__init__.py
src/collective/behavior/sku/behavior.py
src/collective/behavior/sku/configure.zcml
src/collective/behavior/sku/interfaces.py
src/collective/behavior/sku/schema.py
src/collective/behavior/sku/docs/CONTRIBUTORS.rst
src/collective/behavior/sku/docs/CREDITS.rst
src/collective/behavior/sku/docs/HISTORY.rst
src/collective/behavior/sku/docs/LICENSE.rst
src/collective/behavior/sku/locales/collective.behavior.sku.pot
src/collective/behavior/sku/locales/fi/LC_MESSAGES/collective.behavior.sku.mo
src/collective/behavior/sku/locales/fi/LC_MESSAGES/collective.behavior.sku.po
src/collective/behavior/sku/profiles/default/catalog.xml
src/collective/behavior/sku/profiles/default/metadata.xml
src/collective/behavior/sku/tests/__init__.py
src/collective/behavior/sku/tests/base.py
src/collective/behavior/sku/tests/test_ISKU.py
src/collective/behavior/sku/tests/test_SKU.py
src/collective/behavior/sku/tests/test_functional.py
src/collective/behavior/sku/tests/test_setup.py
src/collective/behavior/sku/tests/dexterity/__init__.py
src/collective/behavior/sku/tests/dexterity/configure.zcml
src/collective/behavior/sku/tests/dexterity/folder.py
src/collective/behavior/sku/tests/dexterity/validator.py
src/collective/behavior/sku/tests/dexterity/profiles/default/types.xml
src/collective/behavior/sku/tests/dexterity/profiles/default/types/collective.behavior.sku.Folder.xml
src/collective/behavior/sku/tests/functional/browser.txt